sense/__init__.py
sense/common.py
sense/client/__init__.py
sense/client/address_api.py
sense/client/apiclient.py
sense/client/discover_api.py
sense/client/instance_api.py
sense/client/intent_api.py
sense/client/logging_api.py
sense/client/metadata_api.py
sense/client/profile_api.py
sense/client/requestwrapper.py
sense/client/task_api.py
sense/client/workflow_combined_api.py
sense/client/workflow_phased_api.py
sense/client/siterm/__init__.py
sense/client/siterm/base_api.py
sense/client/siterm/debug_api.py
sense/client/siterm/deltas_api.py
sense/client/siterm/frontend_api.py
sense/client/siterm/models_api.py
sense/client/siterm/requestwrapper.py
sense/client/siterm/services_api.py
sense/models/__init__.py
sense/models/bandwidth.py
sense/models/capability_description.py
sense/models/connection.py
sense/models/connection_bandwidth.py
sense/models/connection_path_tprofile.py
sense/models/connection_schedule.py
sense/models/connection_suggest_ip_range.py
sense/models/connection_terminals.py
sense/models/delta.py
sense/models/discover_description.py
sense/models/discover_description_end_points.py
sense/models/dnc_schema.py
sense/models/dnc_schema_data.py
sense/models/domain_description.py
sense/models/domain_description_edge_points.py
sense/models/full_profile.py
sense/models/inline_response200.py
sense/models/intent.py
sense/models/intent_expanded.py
sense/models/log.py
sense/models/log_level.py
sense/models/logging_configuration.py
sense/models/logging_configuration_loggers.py
sense/models/one_of_service_intent_data.py
sense/models/operation.py
sense/models/path.py
sense/models/profile_edit.py
sense/models/profile_license.py
sense/models/profile_manifest.py
sense/models/service_description.py
sense/models/service_intent.py
sense/models/service_intent_queries.py
sense/models/service_intent_response.py
sense/models/slim_profile.py
sense/models/terminal.py
sense/models/verification_result.py
sense/workflow/__init__.py
sense/workflow/controller.py
sense_o_api-1.42.dist-info/licenses/LICENSE.txt
sense_o_api-1.42.dist-info/METADATA
sense_o_api-1.42.dist-info/WHEEL
sense_o_api-1.42.dist-info/top_level.txt
sense_o_api-1.42.dist-info/RECORD
