Metadata-Version: 2.4
Name: sense_o_api
Version: 1.42
Summary: SENSE-Orchestrator Northbound API Client
Home-page: https://github.com/esnet/StackV
Author: Xi Yang
Classifier: Programming Language :: Python :: 3
Classifier: License :: OSI Approved :: MIT License
Classifier: Operating System :: OS Independent
Requires-Python: >=3.6
License-File: LICENSE.txt
Requires-Dist: six
Requires-Dist: requests
Requires-Dist: pyyaml
Requires-Dist: pytest
Requires-Dist: GitPython
Requires-Dist: zipp
Requires-Dist: urllib3
Requires-Dist: jsonpath_ng
Requires-Dist: certifi>=2022.12.7
Dynamic: author
Dynamic: classifier
Dynamic: description
Dynamic: description-content-type
Dynamic: home-page
Dynamic: license-file
Dynamic: requires-dist
Dynamic: requires-python
Dynamic: summary
